pyipmi/__init__.py
pyipmi/bmc.py
pyipmi/chassis.py
pyipmi/constants.py
pyipmi/dcmi.py
pyipmi/emulation.py
pyipmi/errors.py
pyipmi/event.py
pyipmi/fields.py
pyipmi/fru.py
pyipmi/helper.py
pyipmi/hpm.py
pyipmi/ipmitool.py
pyipmi/lan.py
pyipmi/logger.py
pyipmi/messaging.py
pyipmi/picmg.py
pyipmi/sdr.py
pyipmi/sel.py
pyipmi/sensor.py
pyipmi/session.py
pyipmi/state.py
pyipmi/utils.py
pyipmi/version.py
pyipmi/interfaces/__init__.py
pyipmi/interfaces/aardvark.py
pyipmi/interfaces/ipmb.py
pyipmi/interfaces/ipmbdev.py
pyipmi/interfaces/ipmitool.py
pyipmi/interfaces/mock.py
pyipmi/interfaces/rmcp.py
pyipmi/msgs/__init__.py
pyipmi/msgs/bmc.py
pyipmi/msgs/chassis.py
pyipmi/msgs/constants.py
pyipmi/msgs/dcmi.py
pyipmi/msgs/device_messaging.py
pyipmi/msgs/event.py
pyipmi/msgs/fru.py
pyipmi/msgs/hpm.py
pyipmi/msgs/lan.py
pyipmi/msgs/message.py
pyipmi/msgs/picmg.py
pyipmi/msgs/registry.py
pyipmi/msgs/sdr.py
pyipmi/msgs/sel.py
pyipmi/msgs/sensor.py
pyipmi/msgs/session.py
pyipmi/msgs/vita.py
python_ipmi-0.5.7.dist-info/AUTHORS
python_ipmi-0.5.7.dist-info/COPYING
python_ipmi-0.5.7.dist-info/METADATA
python_ipmi-0.5.7.dist-info/WHEEL
python_ipmi-0.5.7.dist-info/entry_points.txt
python_ipmi-0.5.7.dist-info/top_level.txt
python_ipmi-0.5.7.dist-info/RECORD
