Metadata-Version: 2.1
Name: python-ipmi
Version: 0.5.7
Summary: Pure python IPMI library
Home-page: https://github.com/kontron/python-ipmi
Download-URL: https://github.com/kontron/python-ipmi/tarball/0.5.7
Author: Michael Walle, Heiko Thiery
Author-email: michael.walle@kontron.com, heiko.thiery@kontron.com
License: LGPLv2+
Platform: any
Classifier: Development Status :: 3 - Alpha
Classifier: Environment :: Console
Classifier: License :: OSI Approved :: GNU Lesser General Public License v2 or later (LGPLv2+)
Classifier: Natural Language :: English
Classifier: Operating System :: OS Independent
Classifier: Programming Language :: Python :: 3
Classifier: Programming Language :: Python :: 3.7
Classifier: Programming Language :: Python :: 3.8
Classifier: Programming Language :: Python :: 3.9
Classifier: Programming Language :: Python :: 3.10
Classifier: Programming Language :: Python :: 3.11
Classifier: Programming Language :: Python :: 3.12
Classifier: Programming Language :: Python :: 3.13
Classifier: Topic :: Software Development :: Libraries :: Python Modules
License-File: COPYING
License-File: AUTHORS
